[{"name": "Sugar", "id": "1783669883", "preview": "https://ct.mob0.com/Logo/Sugar.png", "characterMap": null, "tags": ["Glossy", "Outline", "Purple", "Rounded", "Valentines"]}, {"name": "Princess", "id": "829964308", "preview": "https://ct.mob0.com/Logo/Princess.png", "characterMap": null, "tags": ["Girly", "Glowing", "Pink", "Valentines"]}, {"name": "Cupid", "id": "622058564", "preview": "https://ct.mob0.com/Logo/Cupid.png", "characterMap": null, "tags": ["Girly", "Holiday", "Outline", "Pink", "Valentines"]}, {"name": "Glitter", "id": "44", "preview": "https://ct.mob0.com/Logo/Glitter.gif", "characterMap": null, "tags": ["Animated", "Pink", "Sparkle", "Valentines"]}, {"name": "Love", "id": "819721038", "preview": "https://ct.mob0.com/Logo/Love.gif", "characterMap": null, "tags": ["Animated", "Girly", "Glowing", "Outline", "Pink", "Valentines"]}, {"name": "Keen", "id": "758279718", "preview": "https://ct.mob0.com/Logo/Keen.png", "characterMap": null, "tags": ["Heavy", "Orange", "Outline"]}, {"name": "Fun", "id": "1009848424", "preview": "https://ct.mob0.com/Logo/Fun.png", "characterMap": null, "tags": ["Orange", "Outline", "Rounded", "Shadow"]}, {"name": "Burning", "id": "4", "preview": "https://ct.mob0.com/Logo/Burning.gif", "characterMap": null, "tags": ["Animated", "Burning", "Fire", "Red"]}, {"name": "Skate", "id": "780833150", "preview": "https://ct.mob0.com/Logo/Skate.png", "characterMap": null, "tags": ["Blue", "Distressed", "Outline", "Stencil"]}, {"name": "White", "id": "732438332", "preview": "https://ct.mob0.com/Logo/White.png", "characterMap": null, "tags": ["Elegant", "Glowing", "Script", "White"]}, {"name": "Tribal", "id": "2975689126", "preview": "https://ct.mob0.com/Logo/Tribal.png", "characterMap": null, "tags": ["Distressed", "Heavy", "Red", "White"]}, {"name": "SAINT", "id": "4516516448", "preview": "https://ct.mob0.com/Logo/SAINT.png", "characterMap": null, "tags": ["Classic", "Elegant", "Glossy", "Gold", "Shiny"]}, {"name": "Trim", "id": "732443655", "preview": "https://ct.mob0.com/Logo/Gold-Trim.png", "characterMap": null, "tags": ["Classic", "Elegant", "Gold", "Script", "Yellow"]}, {"name": "OZONE", "id": "4618063429", "preview": "https://ct.mob0.com/Logo/OZONE.png", "characterMap": null, "tags": ["Blue", "Glossy", "Glowing", "Ice", "Rounded", "Shiny", "Space"]}, {"name": "Legal", "id": "732429307", "preview": "https://ct.mob0.com/Logo/Legal.png", "characterMap": null, "tags": ["Elegant", "Gray"]}, {"name": "Miami", "id": "2854656927", "preview": "https://ct.mob0.com/Logo/Miami.png", "characterMap": null, "tags": ["Blue", "Heavy", "Outline", "Purple"]}, {"name": "Neon", "id": "18", "preview": "https://ct.mob0.com/Logo/Neon.png", "characterMap": null, "tags": ["Blue", "Glowing", "Neon", "Outline", "Rounded"]}, {"name": "Ballerina", "id": "4624104889", "preview": "https://ct.mob0.com/Logo/Ballerina.png", "characterMap": null, "tags": ["Heavy", "Outline", "Pink", "Retro", "Rounded", "Shiny"]}, {"name": "Supernova", "id": "2650967346", "preview": "https://ct.mob0.com/Logo/Supernova.png", "characterMap": null, "tags": ["Glossy", "Gold", "Space", "Yellow"]}, {"name": "Tesla", "id": "4113131447", "preview": "https://ct.mob0.com/Logo/Tesla.png", "characterMap": null, "tags": ["Chrome", "Metal", "Red"]}, {"name": "Trogdor", "id": "4112270507", "preview": "https://ct.mob0.com/Logo/Trogdor.png", "characterMap": null, "tags": ["Distressed", "Fun", "Red"]}, {"name": "Invaders", "id": "4618529410", "preview": "https://ct.mob0.com/Logo/Invaders.png", "characterMap": null, "tags": ["Glossy", "Green", "Retro", "Rounded", "Shiny"]}, {"name": "Easy", "id": "791030843", "preview": "https://ct.mob0.com/Logo/Easy.png", "characterMap": null, "tags": ["Blue", "Casual", "Fun", "Glossy", "Glowing", "Rounded"]}, {"name": "Glossy", "id": "30", "preview": "https://ct.mob0.com/Logo/Glossy.png", "characterMap": null, "tags": ["Brown", "Chrome", "Glossy", "Outline"]}, {"name": "Glow", "id": "4618054285", "preview": "https://ct.mob0.com/Logo/Neon-Glow.png", "characterMap": null, "tags": ["Animated", "Black", "Black", "Girly", "Glowing", "Glowing", "Glowing", "Green", "Neon", "Outline", "Pink", "Purple", "Retro", "Science-Fiction", "Sharp", "Space", "Stencil"]}, {"name": "Simple", "id": "21", "preview": "https://ct.mob0.com/Logo/Simple.png", "characterMap": null, "tags": ["Blue", "Gradient", "Shadow"]}, {"name": "Fantasy", "id": "45", "preview": "https://ct.mob0.com/Logo/Fantasy.png", "characterMap": null, "tags": ["Distressed", "Shadow", "Stone", "Yellow"]}, {"name": "Slab", "id": "17", "preview": "https://ct.mob0.com/Logo/Slab.png", "characterMap": null, "tags": ["Brown", "Distressed", "Gold", "Yellow"]}, {"name": "iText", "id": "37", "preview": "https://ct.mob0.com/Logo/iText.png", "characterMap": null, "tags": ["Casual", "Fun", "Green", "Rounded", "Yellow"]}, {"name": "Plain", "id": "4112952183", "preview": "https://ct.mob0.com/Logo/Plain.png", "characterMap": null, "tags": ["Black", "Classic", "Heavy"]}, {"name": "Magic", "id": "2975674466", "preview": "https://ct.mob0.com/Logo/Dark-Magic.png", "characterMap": null, "tags": []}, {"name": "Pink", "id": "2651216203", "preview": "https://ct.mob0.com/Logo/Hot-Pink.png", "characterMap": null, "tags": ["Heavy", "Pink", "Purple"]}, {"name": "Outline", "id": "25", "preview": "https://ct.mob0.com/Logo/Outline.png", "characterMap": null, "tags": ["Elegant", "Gold", "Gold", "Gradient", "Outline", "Outline", "Rounded", "Script", "Shiny", "White"]}, {"name": "Fire", "id": "13", "preview": "https://ct.mob0.com/Logo/Fire.png", "characterMap": null, "tags": ["Burning", "Distressed", "Fire", "Heavy", "Red", "Yellow"]}, {"name": "Groovy", "id": "789574607", "preview": "https://ct.mob0.com/Logo/Groovy.png", "characterMap": null, "tags": ["Fun", "Gradient", "Purple", "Rounded"]}, {"name": "Caster", "id": "2654162149", "preview": "https://ct.mob0.com/Logo/Caster.png", "characterMap": null, "tags": ["Black", "Chrome", "Gray", "Outline", "Science-Fiction", "Shiny"]}, {"name": "Gunmetal", "id": "852819205", "preview": "https://ct.mob0.com/Logo/Gunmetal.png", "characterMap": null, "tags": ["Glossy", "Glowing", "Gray"]}, {"name": "Out", "id": "2655376160", "preview": "https://ct.mob0.com/Logo/Spaced-Out.png", "characterMap": null, "tags": ["Chrome", "Retro", "Science-Fiction", "Shiny", "Space"]}, {"name": "Romance", "id": "4112260450", "preview": "https://ct.mob0.com/Logo/Romance.png", "characterMap": null, "tags": ["Blue", "Classic", "Elegant", "Script"]}, {"name": "Cup", "id": "4528246004", "preview": "https://ct.mob0.com/Logo/Coffee-Cup.png", "characterMap": null, "tags": ["Brown", "Fun", "Gold", "Retro", "Yellow"]}, {"name": "Water", "id": "830469381", "preview": "https://ct.mob0.com/Logo/Water.png", "characterMap": null, "tags": ["Blue", "Distressed", "Rounded", "Trippy"]}, {"name": "Flick", "id": "622063540", "preview": "https://ct.mob0.com/Logo/Chick-Flick.png", "characterMap": null, "tags": ["Girly", "Outline", "Pink", "Purple"]}, {"name": "Club", "id": "832337804", "preview": "https://ct.mob0.com/Logo/Club.png", "characterMap": null, "tags": ["Neon", "Outline", "Purple", "Red", "Science-Fiction"]}, {"name": "Comic", "id": "9", "preview": "https://ct.mob0.com/Logo/Comic.png", "characterMap": null, "tags": ["Black", "Casual", "Orange", "Outline", "Yellow"]}, {"name": "Astroman", "id": "4112238638", "preview": "https://ct.mob0.com/Logo/Astroman.png", "characterMap": null, "tags": ["Gold", "Heavy", "Science-Fiction", "Sharp"]}, {"name": "Spring", "id": "759902224", "preview": "https://ct.mob0.com/Logo/Spring.png", "characterMap": null, "tags": ["Fun", "Outline", "Purple", "Rounded"]}, {"name": "Gelatin", "id": "4516518098", "preview": "https://ct.mob0.com/Logo/Gelatin.png", "characterMap": null, "tags": ["Fun", "Heavy", "Rounded", "Trippy", "Yellow"]}, {"name": "Cube", "id": "1779834160", "preview": "https://ct.mob0.com/Logo/Ice-Cube.png", "characterMap": null, "tags": ["Blue", "Glossy", "Ice", "Outline", "Sharp"]}, {"name": "Tough", "id": "758282876", "preview": "https://ct.mob0.com/Logo/Tough.png", "characterMap": null, "tags": ["Distressed", "Glowing", "Gray", "Stencil"]}, {"name": "Scavenge", "id": "4110551533", "preview": "https://ct.mob0.com/Logo/Scavenge.png", "characterMap": null, "tags": ["Heavy", "Medieval", "Metal", "Red", "Sharp"]}, {"name": "Bar", "id": "757794054", "preview": "https://ct.mob0.com/Logo/Gold-Bar.png", "characterMap": null, "tags": ["Chrome", "Glossy", "Gold", "Heavy", "Yellow"]}, {"name": "Vampire", "id": "732414977", "preview": "https://ct.mob0.com/Logo/Vampire.png", "characterMap": null, "tags": ["Classic", "Elegant", "Medieval", "Orange", "Red"]}, {"name": "Christmas", "id": "2222568262", "preview": "https://ct.mob0.com/Logo/Merry-Christmas.png", "characterMap": null, "tags": ["Elegant", "Glowing", "Gold", "Holiday"]}, {"name": "One", "id": "7", "preview": "https://ct.mob0.com/Logo/Chrome-One.png", "characterMap": null, "tags": ["Chrome"]}, {"name": "Stone", "id": "732440996", "preview": "https://ct.mob0.com/Logo/Epic-Stone.png", "characterMap": null, "tags": ["Brown", "Glossy", "Outline", "Sharp", "Stone"]}, {"name": "TROY", "id": "4623632030", "preview": "https://ct.mob0.com/Logo/TROY.png", "characterMap": null, "tags": ["Gold", "Medieval", "Metal", "Shadow"]}, {"name": "Achilles", "id": "4623046021", "preview": "https://ct.mob0.com/Logo/Achilles.png", "characterMap": null, "tags": ["Gold", "Medieval", "Metal", "Red", "Shadow"]}, {"name": "Starburst", "id": "22", "preview": "https://ct.mob0.com/Logo/Starburst.png", "characterMap": null, "tags": ["Distressed", "Green", "Heavy", "Science-Fiction", "Space"]}, {"name": "Sushi", "id": "830446526", "preview": "https://ct.mob0.com/Logo/Sushi.png", "characterMap": null, "tags": ["Distressed", "Orange", "Stencil", "Stone", "Yellow"]}, {"name": "Gold", "id": "4516496663", "preview": "https://ct.mob0.com/Logo/Black-Gold.png", "characterMap": null, "tags": ["Black", "Chrome", "Distressed", "Gold", "Gold", "Gold", "Heavy", "Metal", "Shadow", "Sharp", "Shiny", "Yellow"]}, {"name": "Arryn", "id": "783758829", "preview": "https://ct.mob0.com/Logo/House-Arryn.png", "characterMap": null, "tags": ["Blue", "Distressed", "Elegant", "Gradient", "Stone"]}, {"name": "Conan", "id": "4623636111", "preview": "https://ct.mob0.com/Logo/Conan.png", "characterMap": null, "tags": ["Distressed", "Gold", "Medieval", "Metal"]}, {"name": "Royal", "id": "1357657967", "preview": "https://ct.mob0.com/Logo/Royal.png", "characterMap": null, "tags": ["Elegant", "Gold", "Red"]}, {"name": "Creator", "id": "4110593891", "preview": "https://ct.mob0.com/Logo/Graffiti-Creator.png", "characterMap": null, "tags": ["Purple", "Red"]}, {"name": "Stranger", "id": "2792545512", "preview": "https://ct.mob0.com/Logo/Stranger.png", "characterMap": null, "tags": ["Blue", "Green", "Medieval", "Outline"]}, {"name": "Steel", "id": "15", "preview": "https://ct.mob0.com/Logo/Glowing-Steel.png", "characterMap": null, "tags": ["Blue", "Distressed", "Glowing", "Gray", "Metal"]}, {"name": "Acid", "id": "732450628", "preview": "https://ct.mob0.com/Logo/Bad-Acid.png", "characterMap": null, "tags": ["Distressed", "Purple", "Sparkle", "Trippy", "White"]}, {"name": "54", "id": "732453157", "preview": "https://ct.mob0.com/Logo/Studio-54.png", "characterMap": null, "tags": ["Gradient", "Outline", "Retro", "Trippy"]}, {"name": "Patrick", "id": "758277984", "preview": "https://ct.mob0.com/Logo/Saint-Patrick.png", "characterMap": null, "tags": ["Green", "Holiday", "Outline"]}, {"name": "DEEJAY", "id": "4112285956", "preview": "https://ct.mob0.com/Logo/DEEJAY.png", "characterMap": null, "tags": ["Black", "Green", "Heavy"]}, {"name": "Muddy", "id": "615608693", "preview": "https://ct.mob0.com/Logo/Muddy.png", "characterMap": null, "tags": ["Brown", "Distressed", "Heavy"]}, {"name": "Chromium", "id": "33", "preview": "https://ct.mob0.com/Logo/Chromium.png", "characterMap": null, "tags": ["Blue", "Chrome", "Green", "Orange", "Pink", "Purple", "Sparkle", "Yellow"]}, {"name": "Lasers", "id": "611409107", "preview": "https://ct.mob0.com/Logo/Lasers.png", "characterMap": null, "tags": ["Heavy", "Red", "Rounded", "Science-Fiction", "Space", "Stencil"]}, {"name": "Dragon", "id": "1408867449", "preview": "https://ct.mob0.com/Logo/Dragon.png", "characterMap": null, "tags": ["Brown", "Glowing", "Medieval", "Orange", "Stone"]}, {"name": "Core", "id": "43", "preview": "https://ct.mob0.com/Logo/Molten-Core.gif", "characterMap": null, "tags": ["Animated", "Black", "Burning", "Fire", "Red", "Yellow"]}, {"name": "Blinkie", "id": "819515844", "preview": "https://ct.mob0.com/Logo/Blinkie.gif", "characterMap": null, "tags": ["Animated", "Black", "Pink", "Purple", "Sparkle"]}, {"name": "Rage", "id": "749791093", "preview": "https://ct.mob0.com/Logo/Rage.png", "characterMap": null, "tags": ["Glowing", "Medieval", "Neon", "Outline", "Red"]}, {"name": "GIRL", "id": "4618043283", "preview": "https://ct.mob0.com/Logo/PURPLE-GIRL.png", "characterMap": null, "tags": ["Girly", "Glossy", "Purple", "Rounded", "Valentines"]}, {"name": "Lava", "id": "852774362", "preview": "https://ct.mob0.com/Logo/Lava.png", "characterMap": null, "tags": ["Burning", "Distressed", "Fire", "Heavy", "Red"]}, {"name": "Textured", "id": "28", "preview": "https://ct.mob0.com/Logo/3D-Outline-Textured.png", "characterMap": null, "tags": ["Blue", "Green", "Outline", "Rounded", "Shadow"]}, {"name": "Flaming", "id": "1169711118", "preview": "https://ct.mob0.com/Logo/Flaming.gif", "characterMap": null, "tags": ["Animated", "Burning", "Fire", "Red"]}, {"name": "Gradient", "id": "29", "preview": "https://ct.mob0.com/Logo/3D-Outline-Gradient.png", "characterMap": null, "tags": ["Outline", "Pink", "Red", "Shadow", "White"]}, {"name": "Frosty", "id": "36", "preview": "https://ct.mob0.com/Logo/Frosty.png", "characterMap": null, "tags": ["Blue", "Ice", "Outline", "Sparkle", "White"]}, {"name": "Sword", "id": "2172004512", "preview": "https://ct.mob0.com/Logo/Sword.png", "characterMap": null, "tags": ["Brown", "Medieval", "Red", "Stone"]}, {"name": "Dark", "id": "830474754", "preview": "https://ct.mob0.com/Logo/Dark.png", "characterMap": null, "tags": ["Black", "Distressed", "Medieval"]}, {"name": "Halloween", "id": "1408818473", "preview": "https://ct.mob0.com/Logo/Halloween.png", "characterMap": null, "tags": ["Distressed", "Gray", "Holiday", "Medieval", "Metal", "Red"]}, {"name": "Two", "id": "8", "preview": "https://ct.mob0.com/Logo/Chrome-Two.png", "characterMap": null, "tags": ["Chrome", "Gold", "Gray", "Outline"]}, {"name": "Scripted", "id": "732447945", "preview": "https://ct.mob0.com/Logo/Super-Scripted.png", "characterMap": null, "tags": ["Black", "Chrome", "Glowing", "Script"]}, {"name": "Galactica", "id": "599808801", "preview": "https://ct.mob0.com/Logo/Galactica.png", "characterMap": null, "tags": ["Glowing", "Green", "Science-Fiction", "Space", "Stone"]}, {"name": "Embossed", "id": "31", "preview": "https://ct.mob0.com/Logo/Embossed.png", "characterMap": null, "tags": ["Rounded"]}, {"name": "Bevel", "id": "16", "preview": "https://ct.mob0.com/Logo/Gradient-Bevel.png", "characterMap": null, "tags": ["Gradient", "Gray", "Shadow", "Stencil"]}, {"name": "Year", "id": "2222569522", "preview": "https://ct.mob0.com/Logo/Happy-New-Year.png", "characterMap": null, "tags": ["Chrome", "Girly", "Holiday", "Pink", "Purple", "Red", "Sparkle"]}, {"name": "Hot", "id": "833904313", "preview": "https://ct.mob0.com/Logo/Hot.png", "characterMap": null, "tags": ["Burning", "Fire", "Glossy", "Glowing", "Orange", "Red", "Red", "Yellow"]}, {"name": "Felt", "id": "24", "preview": "https://ct.mob0.com/Logo/Felt.png", "characterMap": null, "tags": ["Purple", "Shadow"]}, {"name": "Particle", "id": "39", "preview": "https://ct.mob0.com/Logo/Particle.png", "characterMap": null, "tags": ["Black", "Distressed", "Heavy", "Red", "Science-Fiction", "Space"]}, {"name": "BEVEL", "id": "4112424040", "preview": "https://ct.mob0.com/Logo/GOLD-BEVEL.png", "characterMap": null, "tags": ["Distressed", "Elegant", "Gold"]}, {"name": "Green", "id": "4618522408", "preview": "https://ct.mob0.com/Logo/Neon-Green.png", "characterMap": null, "tags": ["Glowing", "Green", "Neon", "Retro", "Rounded"]}, {"name": "Robot", "id": "2655372531", "preview": "https://ct.mob0.com/Logo/Robot.png", "characterMap": null, "tags": []}, {"name": "Plastic", "id": "42", "preview": "https://ct.mob0.com/Logo/Plastic.png", "characterMap": null, "tags": ["Casual", "Fun", "Glowing", "Pink", "Shiny"]}, {"name": "Dyed", "id": "612444173", "preview": "https://ct.mob0.com/Logo/Tie-Dyed.png", "characterMap": null, "tags": ["Casual", "Fun", "Outline", "Rounded", "Trippy"]}, {"name": "Snowman", "id": "615569527", "preview": "https://ct.mob0.com/Logo/Snowman.png", "characterMap": null, "tags": ["Fun", "Ice", "Orange", "Rounded", "Sparkle"]}, {"name": "Badge", "id": "32", "preview": "https://ct.mob0.com/Logo/Pixel-Badge.gif", "characterMap": null, "tags": ["Orange"]}, {"name": "Neron", "id": "2176267473", "preview": "https://ct.mob0.com/Logo/Neron.png", "characterMap": null, "tags": ["Medieval", "Red"]}, {"name": "Stripe", "id": "1783676518", "preview": "https://ct.mob0.com/Logo/Candy-Stripe.png", "characterMap": null, "tags": ["Glossy", "Pink", "Rounded"]}, {"name": "Iceberg", "id": "783756759", "preview": "https://ct.mob0.com/Logo/Iceberg.png", "characterMap": null, "tags": ["Blue", "Distressed", "Ice"]}, {"name": "Grinch", "id": "1516206867", "preview": "https://ct.mob0.com/Logo/Grinch.png", "characterMap": null, "tags": ["Glossy", "Green", "Heavy", "Holiday", "Rounded"]}, {"name": "Joy", "id": "1516212090", "preview": "https://ct.mob0.com/Logo/Happy-Joy.png", "characterMap": null, "tags": ["Glossy", "Outline", "Red", "White"]}, {"name": "11", "id": "4113153856", "preview": "https://ct.mob0.com/Logo/Apollo-11.png", "characterMap": null, "tags": []}, {"name": "Iced", "id": "34", "preview": "https://ct.mob0.com/Logo/Iced.png", "characterMap": null, "tags": ["Blue", "Ice"]}, {"name": "Cheetah", "id": "783763343", "preview": "https://ct.mob0.com/Logo/Cheetah.png", "characterMap": null, "tags": ["Black", "Brown", "Outline"]}]